shscan/__init__.py
shscan/main.py
shscan-0.2.0.dist-info/LICENSE
shscan-0.2.0.dist-info/METADATA
shscan-0.2.0.dist-info/WHEEL
shscan-0.2.0.dist-info/entry_points.txt
shscan-0.2.0.dist-info/top_level.txt
shscan-0.2.0.dist-info/RECORD
