Metadata-Version: 2.1
Name: shscan
Version: 0.2.0
Summary: A package for checking the security headers of a URL.
Home-page: https://github.com/boyinf/shscan
Author: boyinf
License: MIT
Classifier: Programming Language :: Python :: 3
Classifier: License :: OSI Approved :: MIT License
Classifier: Operating System :: OS Independent
License-File: LICENSE
Requires-Dist: requests
